.DS_Store
dynpri/__init__.py
dynpri/optim.py
dynpri/path_info.py
dynpri/prefecture_data_with_pairs_info_v2.csv
dynpri/utils_simulation.py
dynrank/__init__.py
dynrank/main.py
dynrank/optim.py
dynrank/path_info.py
dynrank/prefecture_data_with_pairs_info_v2.csv
dynrank/utils_simulation.py
dynpri-0.1.0.dist-info/METADATA
dynpri-0.1.0.dist-info/WHEEL
dynpri-0.1.0.dist-info/top_level.txt
dynpri-0.1.0.dist-info/RECORD
