Metadata-Version: 2.1
Name: dynpri
Version: 0.1.0
Home-page: https://github.com/situmshr/Hackathon_vol.10.git
License: MIT
Requires-Python: >=3.11
Requires-Dist: alembic ==1.13.2
Requires-Dist: cloudpickle ==3.0.0
Requires-Dist: colorlog ==6.8.2
Requires-Dist: contourpy ==1.2.1
Requires-Dist: cycler ==0.12.1
Requires-Dist: fonttools ==4.53.1
Requires-Dist: greenlet ==3.0.3
Requires-Dist: gym ==0.26.2
Requires-Dist: gym-notices ==0.0.8
Requires-Dist: joblib ==1.4.2
Requires-Dist: kiwisolver ==1.4.5
Requires-Dist: Mako ==1.3.5
Requires-Dist: MarkupSafe ==2.1.5
Requires-Dist: matplotlib ==3.9.1
Requires-Dist: numpy ==2.0.1
Requires-Dist: optuna ==3.6.1
Requires-Dist: packaging ==24.1
Requires-Dist: pandas ==2.2.2
Requires-Dist: pillow ==10.4.0
Requires-Dist: pyparsing ==3.1.2
Requires-Dist: python-dateutil ==2.9.0.post0
Requires-Dist: pytz ==2024.1
Requires-Dist: PyYAML ==6.0.1
Requires-Dist: scikit-learn ==1.5.1
Requires-Dist: scipy ==1.14.0
Requires-Dist: six ==1.16.0
Requires-Dist: SQLAlchemy ==2.0.31
Requires-Dist: threadpoolctl ==3.5.0
Requires-Dist: tqdm ==4.66.4
Requires-Dist: typing-extensions ==4.12.2
Requires-Dist: tzdata ==2024.1
